remocker.py
remocker-0.3.0.dist-info/METADATA
remocker-0.3.0.dist-info/WHEEL
remocker-0.3.0.dist-info/RECORD
