Metadata-Version: 2.1
Name: remocker
Version: 0.3.0
Summary: mocking http request more easy
Home-page: https://github.com/jrog612/remocker
License: MIT
Author: Jrog
Author-email: jrog612@gmail.com
Requires-Python: >=3.8,<4.0
Classifier: License :: OSI Approved :: MIT License
Classifier: Programming Language :: Python :: 3
Classifier: Programming Language :: Python :: 3.8
Classifier: Programming Language :: Python :: 3.9
Classifier: Programming Language :: Python :: 3.10
Classifier: Programming Language :: Python :: 3.11
Classifier: Programming Language :: Python :: 3.12
Classifier: Programming Language :: Python :: 3.13
Requires-Dist: responses (>=0.25.6,<0.26.0)
Project-URL: Repository, https://github.com/jrog612/remocker
